jwcrypto-stubs/METADATA.toml
jwcrypto-stubs/__init__.pyi
jwcrypto-stubs/common.pyi
jwcrypto-stubs/jwa.pyi
jwcrypto-stubs/jwe.pyi
jwcrypto-stubs/jwk.pyi
jwcrypto-stubs/jws.pyi
jwcrypto-stubs/jwt.pyi
jwcrypto-stubs/py.typed
types_jwcrypto-1.5.0.20250516.dist-info/licenses/LICENSE
types_jwcrypto-1.5.0.20250516.dist-info/METADATA
types_jwcrypto-1.5.0.20250516.dist-info/WHEEL
types_jwcrypto-1.5.0.20250516.dist-info/top_level.txt
types_jwcrypto-1.5.0.20250516.dist-info/RECORD
